urwidtrees/__init__.py
urwidtrees/decoration.py
urwidtrees/lru_cache.py
urwidtrees/nested.py
urwidtrees/tree.py
urwidtrees/version.py
urwidtrees/widgets.py
urwidtrees-1.0.4.dist-info/licenses/LICENSE.md
urwidtrees-1.0.4.dist-info/METADATA
urwidtrees-1.0.4.dist-info/WHEEL
urwidtrees-1.0.4.dist-info/top_level.txt
urwidtrees-1.0.4.dist-info/RECORD
