Metadata-Version: 2.4
Name: urwidtrees
Version: 1.0.4
Summary: Tree widgets for urwid
Home-page: https://github.com/pazz/urwidtrees
Author: Patrick Totzke
Author-email: patricktotzke@gmail.com
License: Licensed under the GNU GPL v3+.
License-File: LICENSE.md
Requires-Dist: urwid>=1.1.0
Provides-Extra: docs
Requires-Dist: mock; python_version < "3.3" and extra == "docs"
Dynamic: author
Dynamic: author-email
Dynamic: home-page
Dynamic: license
Dynamic: license-file
Dynamic: provides-extra
Dynamic: requires-dist
Dynamic: summary
